guacalib/__init__.py
guacalib/cli.py
guacalib/cli_handle_conn.py
guacalib/cli_handle_conngroup.py
guacalib/cli_handle_dump.py
guacalib/cli_handle_user.py
guacalib/cli_handle_usergroup.py
guacalib/db.py
guacalib/db_connection_parameters.py
guacalib/db_user_parameters.py
guacalib/version.py
guacalib-0.23.dist-info/licenses/LICENSE.md
guacalib-0.23.dist-info/METADATA
guacalib-0.23.dist-info/WHEEL
guacalib-0.23.dist-info/entry_points.txt
guacalib-0.23.dist-info/top_level.txt
guacalib-0.23.dist-info/RECORD
