Metadata-Version: 2.4
Name: guacalib
Version: 0.23
Summary: Guacamole management library and CLI
Author-email: "Roman V. Isaev" <rm@isaeff.net>
License-Expression: GPL-3.0-or-later
Classifier: Programming Language :: Python :: 3
Classifier: Operating System :: OS Independent
Requires-Python: >=3.8
License-File: LICENSE.md
Requires-Dist: mysql-connector-python>=8.0.0
Requires-Dist: configparser>=5.0.0
Provides-Extra: dev
Requires-Dist: black; extra == "dev"
Requires-Dist: flake8; extra == "dev"
Requires-Dist: pytest; extra == "dev"
Dynamic: license-file
